.travis.yml
DESCRIPTION.rst
MANIFEST.in
README.txt
definitionfile.def.yml
myconfig.def.yml
myconfig.yml
requirements.txt
setup.py
defconf/__init__.py
defconf.egg-info/PKG-INFO
defconf.egg-info/SOURCES.txt
defconf.egg-info/dependency_links.txt
defconf.egg-info/top_level.txt