Metadata-Version: 1.1
Name: defconf
Version: 0.2.0
Summary: Python Library/tool to easily define and validate the format and content of a configuration file
Home-page: https://github.com/dgarros/defconf
Author: Damien Garros
Author-email: dgarros@gmail.com
License: Apache
Keywords: validationtool definition configuration development
Platform: UNKNOWN
Classifier: Development Status :: 4 - Beta
Classifier: Intended Audience :: Developers
Classifier: License :: OSI Approved :: Apache Software License
Classifier: Topic :: Software Development :: Libraries :: Python Modules
Classifier: Topic :: Utilities
Classifier: Programming Language :: Python :: 2.6
Classifier: Programming Language :: Python :: 2.7
